nobe/__init__.py
nobe/source.py
nobe/theme.py
nobe_literate-0.1.4.dist-info/METADATA
nobe_literate-0.1.4.dist-info/WHEEL
nobe_literate-0.1.4.dist-info/licenses/LICENSE
nobe_literate-0.1.4.dist-info/RECORD
