Metadata-Version: 2.4
Name: nobe-literate
Version: 0.1.4
Summary: A literate programming tool for publishing html documents as a library
Project-URL: repository, https://github.com/pietroppeter/nobe
Project-URL: issue-tracker, https://github.com/pietroppeter/nobe/issues
Author: Pietro Peterlongo
License-Expression: MIT
License-File: LICENSE
Classifier: License :: OSI Approved :: MIT License
Classifier: Operating System :: OS Independent
Classifier: Programming Language :: Python :: 3
Requires-Python: >=3.9
Requires-Dist: markdown>=3.7
Requires-Dist: pydantic>=2.10.6
